AUTHORS.rst
LICENSE
MANIFEST.in
README.rst
setup.py
django_shop_saferpay.egg-info/PKG-INFO
django_shop_saferpay.egg-info/SOURCES.txt
django_shop_saferpay.egg-info/dependency_links.txt
django_shop_saferpay.egg-info/not-zip-safe
django_shop_saferpay.egg-info/requires.txt
django_shop_saferpay.egg-info/top_level.txt
saferpay_backend/__init__.py
saferpay_backend/models.py
saferpay_backend/saferpay.py
saferpay_backend/settings.py
saferpay_backend/tasks.py
saferpay_backend/locale/de/LC_MESSAGES/django.mo
saferpay_backend/locale/de/LC_MESSAGES/django.po
saferpay_backend/locale/fr/LC_MESSAGES/django.mo
saferpay_backend/locale/fr/LC_MESSAGES/django.po
saferpay_backend/templates/saferpay_backend/cancel.html
saferpay_backend/templates/saferpay_backend/failure.html