Metadata-Version: 1.0
Name: django-shop-saferpay
Version: 1.2.0
Summary: A django SHOP payment backend for SaferPay
Home-page: https://github.com/piquadrat/django-shop-saferpay
Author: Benjamin Wohlwend
Author-email: piquadrat@gmail.com
License: UNKNOWN
Platform: UNKNOWN
Classifier: Development Status :: 3 - Alpha
Classifier: Framework :: Django
Classifier: Intended Audience :: Developers
Classifier: License :: OSI Approved :: BSD License
Classifier: Operating System :: OS Independent
Classifier: Programming Language :: Python :: 2.6
Classifier: Programming Language :: Python :: 2.7
Classifier: Topic :: Software Development
Classifier: Topic :: Internet :: WWW/HTTP :: Dynamic Content
